tsdbadmin/__init__.py
tsdbadmin/database_list_widget.cp313-win_amd64.pyd
tsdbadmin/database_login_dialog.cp313-win_amd64.pyd
tsdbadmin/enhanced_tags_table.cp313-win_amd64.pyd
tsdbadmin/multi_table_tabs.cp313-win_amd64.pyd
tsdbadmin/postgresql_utils.cp313-win_amd64.pyd
tsdbadmin/qt_compat_exec.cp313-win_amd64.pyd
tsdbadmin/quick_export.cp313-win_amd64.pyd
tsdbadmin/quick_import.cp313-win_amd64.pyd
tsdbadmin/table_widget2.cp313-win_amd64.pyd
tsdbadmin/tsdb_manager_main.cp313-win_amd64.pyd
tsdbadmin/pics/manager_icon.ico
tsdbadmin-1.1.1.dist-info/METADATA
tsdbadmin-1.1.1.dist-info/WHEEL
tsdbadmin-1.1.1.dist-info/top_level.txt
tsdbadmin-1.1.1.dist-info/RECORD
